<?xml version="1.0" encoding="UTF-8"?>
<includes>

	<include name="Viewtype56">

		<control type="group">
			<visible>Control.IsVisible(56)</visible>

			<!-- Curve -->
			<control type="image">
				<right>20</right>
				<top>20</top>
				<width>1380</width>
				<height>1040</height>
				<texture border="40,0,0,0">common/Curve.png</texture>
				<visible>Skin.HasSetting(ShowCurve)</visible>
			</control>

			<!-- List -->
			<control type="list" id="56">
				<left>120</left>
				<top>225</top>
				<width>305</width>
				<height>720</height>
				<onup>51</onup>
				<ondown>51</ondown>
				<onleft>60</onleft>
				<onright condition="!Skin.HasSetting(KioskMode)">3001</onright>
				<pagecontrol>60</pagecontrol>
				<orientation>vertical</orientation>
				<viewtype label="Aliter">list</viewtype>
				<scrolltime tween="sine" easing="out">240</scrolltime>
				<visible>Window.IsVisible(Music) | [Container.Content(songs) + Window.IsVisible(musicplaylist)] | [!Container.Content(movies) + !Container.Content(tvshows) + !Container.Content(seasons) + !Container.Content(episodes) + !Container.Content(albums) + !Container.Content(songs) + !Window.IsVisible(pictures)]</visible>

				<itemlayout height="90" width="305">
					<control type="label">
						<left>0</left>
						<top>0</top>
						<width>305</width>
						<height>90</height>
						<font>Font36</font>
						<label>$VAR[Label1]</label>
						<textcolor>$VAR[TextColor2]</textcolor>
					</control>
				</itemlayout>

				<focusedlayout height="90" width="305">
					<control type="label">
						<left>0</left>
						<top>0</top>
						<width>305</width>
						<height>90</height>
						<font>Font36</font>
						<label>$VAR[Label1]</label>
						<textcolor>$VAR[TextColor1]</textcolor>
						<animation effect="fade" start="100" end="50" time="200" tween="cubic" easing="out" reversible="true" condition="!Control.HasFocus(56)">Conditional</animation>
					</control>
				</focusedlayout>

			</control>

			<!-- Debug -->
			<control type="label">
				<left>750</left>
				<centertop>50%</centertop>
				<width>1050</width>
				<height>720</height>
				<font>Font36</font>
				<label>$INFO[Window(10000).Property(NodeHelper_Widget)][CR]$INFO[Window(10000).Property(NodeHelper_WidgetName)][CR]$INFO[Window(10000).Property(NodeHelper_WidgetType)][CR]$INFO[Window(10000).Property(NodeHelper_WidgetTarget)][CR]$INFO[Window(10000).Property(NodeHelper_WidgetPath)][CR][CR]$INFO[Window(10000).Property(NodeHelper_Widget_2)][CR]$INFO[Window(10000).Property(NodeHelper_WidgetName_2)][CR]$INFO[Window(10000).Property(NodeHelper_WidgetType_2)][CR]$INFO[Window(10000).Property(NodeHelper_WidgetTarget_2)][CR]$INFO[Window(10000).Property(NodeHelper_WidgetPath_2)]</label>
				<textcolor>$VAR[TextColor2]</textcolor>
			</control>

			<!-- Widget 1 -->
			<control id="8000" type="list">
				<left>2605</left>
				<top>200</top>
				<width>1218</width>
				<height>306</height>
				<onleft>9000</onleft>
				<onback>9000</onback>
				<onright>noop</onright>
				<viewtype label="">list</viewtype>
				<orientation>horizontal</orientation>
				<defaultcontrol always="true">0</defaultcontrol>
				<scrolltime easing="out" tween="sine">240</scrolltime>
				<animation condition="True + StringCompare(Container(8000).NumItems,1)" effect="slide" end="-1000,0" start="0,0" time="0">conditional</animation>
				<animation condition="True + StringCompare(Container(8000).NumItems,2)" effect="slide" end="-1203,0" start="0,0" time="0">conditional</animation>
				<animation condition="True + StringCompare(Container(8000).NumItems,3)" effect="slide" end="-1406,0" start="0,0" time="0">conditional</animation>
				<animation condition="True + StringCompare(Container(8000).NumItems,4)" effect="slide" end="-1609,0" start="0,0" time="0">conditional</animation>
				<animation condition="True + StringCompare(Container(8000).NumItems,5)" effect="slide" end="-1812,0" start="0,0" time="0">conditional</animation>
				<animation condition="True + IntegerGreaterThan(Container(8000).NumItems,5)" effect="slide" end="-2015,0" start="0,0" time="0">conditional</animation>
				<animation condition="False + StringCompare(Container(8000).NumItems,1)" effect="slide" end="-1325,0" start="0,0" time="0">conditional</animation>
				<animation condition="False + StringCompare(Container(8000).NumItems,2)" effect="slide" end="-1670,0" start="0,0" time="0">conditional</animation>
				<animation condition="False + IntegerGreaterThan(Container(8000).NumItems,2)" effect="slide" end="-2015,0" start="0,0" time="0">conditional</animation>
				<animation type="visible">
					<effect delay="100" end="100" start="0" time="200" type="fade" />
					<effect delay="100" end="0,0" start="600,0" time="200" type="slide" />
				</animation>
				<animation type="hidden">
					<effect end="0" start="100" time="200" type="fade" />
					<effect end="600,0" start="0,0" time="200" type="slide" />
				</animation>
				<itemlayout height="306" width="203">
					<include content="widget-image">
						<description>Primary art</description>
						<param name="width">183</param>
						<param name="height">306</param>
						<param name="colordiffuse">DiffusePosterNF</param>
						<param name="fallback" />
						<param name="art">$INFO[ListItem.Art(poster)]</param>
						<param name="aspectratio">keep</param>
						<param name="shadow">views/DropShadowSmall.png</param>
						<param name="visible" />
					</include>
					<include content="widget-image">
						<description>Fallback art</description>
						<param name="width">183</param>
						<param name="height">306</param>
						<param name="colordiffuse">DiffusePosterNF</param>
						<param name="fallback" />
						<param name="art">$INFO[ListItem.Icon]</param>
						<param name="aspectratio">keep</param>
						<param name="shadow">views/DropShadowSmall.png</param>
						<param name="visible">IsEmpty(ListItem.Art(poster))</param>
					</include>
					<include content="widget-image">
						<description>Catch-all art</description>
						<param name="width">183</param>
						<param name="height">306</param>
						<param name="colordiffuse">DiffusePosterNF</param>
						<param name="fallback">DefaultShortcut.png</param>
						<param name="art">$INFO[ListItem.Icon]</param>
						<param name="aspectratio">keep</param>
						<param name="shadow">views/DropShadowSmall.png</param>
						<param name="visible">[ IsEmpty(ListItem.Art(poster)) ] + [ IsEmpty(ListItem.Icon) ]</param>
					</include>
					<control type="image">
						<left>138</left>
						<top>256</top>
						<width>35</width>
						<height>49</height>
						<texture>$VAR[StatusOverlayWide]</texture>
						<visible>!Skin.HasSetting(widgetIcons)</visible>
					</control>
				</itemlayout>
				<focusedlayout height="306" width="203">
					<control type="group">
						<include content="widget-image">
							<description>Primary art</description>
							<param name="width">183</param>
							<param name="height">306</param>
							<param name="colordiffuse" />
							<param name="fallback" />
							<param name="art">$INFO[ListItem.Art(poster)]</param>
							<param name="aspectratio">keep</param>
							<param name="shadow">views/DropShadowSmall.png</param>
							<param name="visible" />
						</include>
						<include content="widget-image">
							<description>Fallback art</description>
							<param name="width">183</param>
							<param name="height">306</param>
							<param name="colordiffuse" />
							<param name="fallback" />
							<param name="art">$INFO[ListItem.Icon]</param>
							<param name="aspectratio">keep</param>
							<param name="shadow">views/DropShadowSmall.png</param>
							<param name="visible">IsEmpty(ListItem.Art(poster))</param>
						</include>
						<include content="widget-image">
							<description>Catch-all art</description>
							<param name="width">183</param>
							<param name="height">306</param>
							<param name="colordiffuse" />
							<param name="fallback">DefaultShortcut.png</param>
							<param name="art">$INFO[ListItem.Icon]</param>
							<param name="aspectratio">keep</param>
							<param name="shadow">views/DropShadowSmall.png</param>
							<param name="visible">[ IsEmpty(ListItem.Art(poster)) ] + [ IsEmpty(ListItem.Icon) ]</param>
						</include>
						<visible>Control.HasFocus(8000)</visible>
					</control>
					<control type="group">
						<include content="widget-image">
							<description>Primary art</description>
							<param name="width">183</param>
							<param name="height">306</param>
							<param name="colordiffuse">DiffusePosterNF</param>
							<param name="fallback" />
							<param name="art">$INFO[ListItem.Art(poster)]</param>
							<param name="aspectratio">keep</param>
							<param name="shadow">views/DropShadowSmall.png</param>
							<param name="visible" />
						</include>
						<include content="widget-image">
							<description>Fallback art</description>
							<param name="width">183</param>
							<param name="height">306</param>
							<param name="colordiffuse">DiffusePosterNF</param>
							<param name="fallback" />
							<param name="art">$INFO[ListItem.Icon]</param>
							<param name="aspectratio">keep</param>
							<param name="shadow">views/DropShadowSmall.png</param>
							<param name="visible">IsEmpty(ListItem.Art(poster))</param>
						</include>
						<include content="widget-image">
							<description>Catch-all art</description>
							<param name="width">183</param>
							<param name="height">306</param>
							<param name="colordiffuse">DiffusePosterNF</param>
							<param name="fallback">DefaultShortcut.png</param>
							<param name="art">$INFO[ListItem.Icon]</param>
							<param name="aspectratio">keep</param>
							<param name="shadow">views/DropShadowSmall.png</param>
							<param name="visible">[ IsEmpty(ListItem.Art(poster)) ] + [ IsEmpty(ListItem.Icon) ]</param>
						</include>
						<visible>!Control.HasFocus(8000)</visible>
					</control>
					<control type="image">
						<left>138</left>
						<top>256</top>
						<width>35</width>
						<height>49</height>
						<texture>$VAR[StatusOverlayWide]</texture>
						<visible>!Skin.HasSetting(widgetIcons)</visible>
					</control>
				</focusedlayout>
				<content target="videos">$INFO[Window(10000).Property(NodeHelper_WidgetPath)]</content>
			</control>
			<control type="grouplist">
				<animation effect="fade" end="0" start="100" time="0">Hidden</animation>
				<animation delay="100" effect="fade" end="100" start="0" time="200">Visible</animation>
				<top>1005</top>
				<right>120</right>
				<width>1000</width>
				<height>33</height>
				<align>right</align>
				<aligny>center</aligny>
				<orientation>horizontal</orientation>
				<itemgap>10</itemgap>
				<control type="image">
					<width>33</width>
					<height>33</height>
					<texture>busy.gif</texture>
					<visible>Container(8000).IsUpdating</visible>
				</control>
				<control type="label">
					<minwidth>10</minwidth>
					<maxwidth>950</maxwidth>
					<width>auto</width>
					<height>33</height>
					<font>Font33</font>
					<textcolor>$VAR[SubMenuColor]</textcolor>
					<label>Hello$INFO[Window(10000).Property(NodeHelper_WidgetName)]</label>
				</control>
			</control>

			<!-- Widget 2 -->
			<control id="8001" type="list">
				<left>2605</left>
				<top>550</top>
				<width>1218</width>
				<height>306</height>
				<onleft>9000</onleft>
				<onback>9000</onback>
				<onright>noop</onright>
				<viewtype label="">list</viewtype>
				<orientation>horizontal</orientation>
				<defaultcontrol always="true">0</defaultcontrol>
				<scrolltime easing="out" tween="sine">240</scrolltime>
				<animation condition="True + StringCompare(Container(8001).NumItems,1)" effect="slide" end="-1000,0" start="0,0" time="0">conditional</animation>
				<animation condition="True + StringCompare(Container(8001).NumItems,2)" effect="slide" end="-1203,0" start="0,0" time="0">conditional</animation>
				<animation condition="True + StringCompare(Container(8001).NumItems,3)" effect="slide" end="-1406,0" start="0,0" time="0">conditional</animation>
				<animation condition="True + StringCompare(Container(8001).NumItems,4)" effect="slide" end="-1609,0" start="0,0" time="0">conditional</animation>
				<animation condition="True + StringCompare(Container(8001).NumItems,5)" effect="slide" end="-1812,0" start="0,0" time="0">conditional</animation>
				<animation condition="True + IntegerGreaterThan(Container(8001).NumItems,5)" effect="slide" end="-2015,0" start="0,0" time="0">conditional</animation>
				<animation condition="False + StringCompare(Container(8001).NumItems,1)" effect="slide" end="-1325,0" start="0,0" time="0">conditional</animation>
				<animation condition="False + StringCompare(Container(8001).NumItems,2)" effect="slide" end="-1670,0" start="0,0" time="0">conditional</animation>
				<animation condition="False + IntegerGreaterThan(Container(8001).NumItems,2)" effect="slide" end="-2015,0" start="0,0" time="0">conditional</animation>
				<animation type="visible">
					<effect delay="100" end="100" start="0" time="200" type="fade" />
					<effect delay="100" end="0,0" start="600,0" time="200" type="slide" />
				</animation>
				<animation type="hidden">
					<effect end="0" start="100" time="200" type="fade" />
					<effect end="600,0" start="0,0" time="200" type="slide" />
				</animation>
				<itemlayout height="306" width="203">
					<include content="widget-image">
						<description>Primary art</description>
						<param name="width">183</param>
						<param name="height">306</param>
						<param name="colordiffuse">DiffusePosterNF</param>
						<param name="fallback" />
						<param name="art">$INFO[ListItem.Art(season.poster)]</param>
						<param name="aspectratio">keep</param>
						<param name="shadow">views/DropShadowSmall.png</param>
						<param name="visible" />
						<param name="aligny">top</param>
					</include>
					<include content="widget-image">
						<description>Fallback art</description>
						<param name="width">183</param>
						<param name="height">306</param>
						<param name="colordiffuse">DiffusePosterNF</param>
						<param name="fallback" />
						<param name="art">$INFO[ListItem.Art(poster)]</param>
						<param name="aspectratio">keep</param>
						<param name="shadow">views/DropShadowSmall.png</param>
						<param name="visible">IsEmpty(ListItem.Art(season.poster))</param>
						<param name="aligny">top</param>
					</include>
					<include content="widget-image">
						<description>Catch-all art</description>
						<param name="width">183</param>
						<param name="height">306</param>
						<param name="colordiffuse">DiffusePosterNF</param>
						<param name="fallback">DefaultShortcut.png</param>
						<param name="art">$INFO[ListItem.Icon]</param>
						<param name="aspectratio">keep</param>
						<param name="shadow">views/DropShadowSmall.png</param>
						<param name="visible">[ IsEmpty(ListItem.Art(season.poster)) ] + [ IsEmpty(ListItem.Art(poster)) ]</param>
						<param name="aligny">top</param>
					</include>
					<control type="image">
						<left>138</left>
						<top>256</top>
						<width>35</width>
						<height>49</height>
						<texture>$VAR[StatusOverlayWide]</texture>
						<visible>!Skin.HasSetting(widgetIcons)</visible>
					</control>
				</itemlayout>
				<focusedlayout height="306" width="203">
					<control type="group">
						<include content="widget-image">
							<description>Primary art</description>
							<param name="width">183</param>
							<param name="height">306</param>
							<param name="colordiffuse" />
							<param name="fallback" />
							<param name="art">$INFO[ListItem.Art(season.poster)]</param>
							<param name="aspectratio">keep</param>
							<param name="shadow">views/DropShadowSmall.png</param>
							<param name="visible" />
							<param name="aligny">top</param>
						</include>
						<include content="widget-image">
							<description>Fallback art</description>
							<param name="width">183</param>
							<param name="height">306</param>
							<param name="colordiffuse" />
							<param name="fallback" />
							<param name="art">$INFO[ListItem.Art(poster)]</param>
							<param name="aspectratio">keep</param>
							<param name="shadow">views/DropShadowSmall.png</param>
							<param name="visible">IsEmpty(ListItem.Art(poster))</param>
							<param name="aligny">top</param>
						</include>
						<include content="widget-image">
							<description>Catch-all art</description>
							<param name="width">183</param>
							<param name="height">306</param>
							<param name="colordiffuse" />
							<param name="fallback">DefaultShortcut.png</param>
							<param name="art">$INFO[ListItem.Icon]</param>
							<param name="aspectratio">keep</param>
							<param name="shadow">views/DropShadowSmall.png</param>
							<param name="visible">[ IsEmpty(ListItem.Art(season.poster)) ] + [ IsEmpty(ListItem.Art(poster)) ]</param>
							<param name="aligny">top</param>
						</include>
						<visible>Control.HasFocus(8001)</visible>
					</control>
					<control type="group">
						<include content="widget-image">
							<description>Primary art</description>
							<param name="width">183</param>
							<param name="height">306</param>
							<param name="colordiffuse">DiffusePosterNF</param>
							<param name="fallback" />
							<param name="art">$INFO[ListItem.Art(season.poster)]</param>
							<param name="aspectratio">keep</param>
							<param name="shadow">views/DropShadowSmall.png</param>
							<param name="visible" />
							<param name="aligny">top</param>
						</include>
						<include content="widget-image">
							<description>Fallback art</description>
							<param name="width">183</param>
							<param name="height">306</param>
							<param name="colordiffuse">DiffusePosterNF</param>
							<param name="fallback" />
							<param name="art">$INFO[ListItem.Art(poster)]</param>
							<param name="aspectratio">keep</param>
							<param name="shadow">views/DropShadowSmall.png</param>
							<param name="visible">IsEmpty(ListItem.Art(season.poster))</param>
							<param name="aligny">top</param>
						</include>
						<include content="widget-image">
							<description>Catch-all art</description>
							<param name="width">183</param>
							<param name="height">306</param>
							<param name="colordiffuse">DiffusePosterNF</param>
							<param name="fallback">DefaultShortcut.png</param>
							<param name="art">$INFO[ListItem.Icon]</param>
							<param name="aspectratio">keep</param>
							<param name="shadow">views/DropShadowSmall.png</param>
							<param name="visible">[ IsEmpty(ListItem.Art(season.poster)) ] + [ IsEmpty(ListItem.Art(poster)) ]</param>
							<param name="aligny">top</param>
						</include>
						<visible>!Control.HasFocus(8001)</visible>
					</control>
					<control type="image">
						<left>138</left>
						<top>256</top>
						<width>35</width>
						<height>49</height>
						<texture>$VAR[StatusOverlayWide]</texture>
						<visible>!Skin.HasSetting(widgetIcons)</visible>
					</control>
				</focusedlayout>
				<content target="videos">$INFO[Window(10000).Property(NodeHelper_WidgetPath_2)]</content>
			</control>
			<control type="grouplist">
				<animation effect="fade" end="0" start="100" time="0">Hidden</animation>
				<animation delay="100" effect="fade" end="100" start="0" time="200">Visible</animation>
				<top>1005</top>
				<right>120</right>
				<width>1000</width>
				<height>33</height>
				<align>right</align>
				<aligny>center</aligny>
				<orientation>horizontal</orientation>
				<itemgap>10</itemgap>
				<control type="image">
					<width>33</width>
					<height>33</height>
					<texture>busy.gif</texture>
					<visible>Container(8001).IsUpdating</visible>
				</control>
				<control type="label">
					<minwidth>10</minwidth>
					<maxwidth>950</maxwidth>
					<width>auto</width>
					<height>33</height>
					<font>Font33</font>
					<textcolor>$VAR[SubMenuColor]</textcolor>
					<label>Hello$INFO[Window(10000).Property(NodeHelper_WidgetName_2)]</label>
				</control>
			</control>


		</control>

	</include>

</includes>
